ChangeLog.rst
LICENSE
MANIFEST.in
README.rst
setup.py
mrep/__init__.py
mrep/builder.py
mrep/morph.py
mrep/pattern.py
mrep/printer.py
mrep.egg-info/PKG-INFO
mrep.egg-info/SOURCES.txt
mrep.egg-info/dependency_links.txt
mrep.egg-info/requires.txt
mrep.egg-info/top_level.txt
scripts/mrep
test/__init__.py
test/builder_test.py
test/morph_test.py
test/mrep_test.py
test/pattern_test.py
test/printer_test.py
test/data/1.txt
test/data/1_dot.result
test/data/1_nocolor_dot.result
test/data/1_nocolor_noun.result
test/data/1_nocolor_noun_or_verb.result
test/data/1_nocolor_noun_particle.result
test/data/1_nocolor_verb.result
test/data/1_noun_or_verb.result
test/data/1_noun_particle.result
test/data/1_verb.result