Metadata-Version: 1.1
Name: mrep
Version: 0.1.1
Summary: MREP: morpheme regular expression printer
Home-page: https://github.com/unnonouno/mrep
Author: Yuya Unno
Author-email: unnonouno@gmail.com
License: MIT
Platform: UNKNOWN
Classifier: Operating System :: OS Independent
Classifier: Environment :: Console
Classifier: Programming Language :: Python
Classifier: License :: OSI Approved :: MIT License
Classifier: Development Status :: 2 - Pre-Alpha
Classifier: Intended Audience :: Information Technology
Classifier: Intended Audience :: Science/Research
Classifier: Topic :: Utilities
